iniconf
