Metadata-Version: 1.0
Name: iniconf
Version: 0.1.9.1
Summary: INI Config Creating/Parsing Tool
Home-page: https://github.com/brunogfranca/iniconf
Author: Bruno Franca
Author-email: bgfranca@gmail.com
License: The MIT License
